LICENSE.GPL
MANIFEST.in
Makefile
README
TODO
__pkginfo__.py
__version__.py
ez_setup.py
setup.py
valgrind-python.supp
Chimera/__init__.py
Chimera/chimera_recipe.py
Chimera/chimera_tool.py
Chimera/chimera_widgets.py
Chimera/config.py
Chimera/imageadapter.py
Chimera/refresh.txt
Chimera/tool.png
Chimera/Extensions/Install.py
Chimera/Extensions/__init__.py
Chimera/Extensions/test_chimera.py
Chimera/Extensions/text_chimera.py
Chimera/Extensions/text_over_chimera.py
Chimera/skins/chimara_skin/blingtext_chimera.py
Chimera/skins/chimara_skin/chimeraL.py
Chimera/skins/chimara_skin/chimeraLive.js.dtml
Chimera/skins/chimara_skin/chimeraTextTest.pt
Chimera/skins/chimara_skin/chimera_image_widget.pt
Chimera/skins/chimara_skin/chimeraview.pt
Chimera/tests/__init__.py
Chimera/tests/framework.py
Chimera/tests/runalltests.py
Chimera/tests/test_project.py
chimera.egg-info/PKG-INFO
chimera.egg-info/SOURCES.txt
chimera.egg-info/dependency_links.txt
chimera.egg-info/native_libs.txt
chimera.egg-info/requires.txt
chimera.egg-info/top_level.txt
distext/__init__.py
distext/build_ext.py
distext/doc.py
distext/install.py
distext/pkgconfig.py
distext/test.py
distext/utils.py
docs/INSTALL.txt
docs/Makefile
docs/getbuildpath.py
docs/writedocs.py
docs/examples/watermark.py
src/__init__.py
src/cairo.pxd
src/cairo.pyx
src/chimera.py
src/chimera_pango.pyx
src/chimera_png.pyx
src/chimera_svg.pyx
src/colors.py
src/common.pyi
src/fontconfig.pxd
src/fontconfig.pyx
src/glib.pxd
src/libc.pxd
src/pango.pxd
src/pangocairo.pyx
src/python.pxd
src/usage.txt
src/utils.py
tests/COULON.TTF
tests/COURIERO.TTF
tests/GLASS.utf8
tests/HELLO.utf8
tests/Makefile
tests/__init__.py
tests/_test_cairo.py
tests/kapow.png
tests/logo.jpg
tests/logo.png
tests/logo.svg
tests/plus.png
tests/runalltests.py
tests/star.png
tests/test_chimera.py
tests/test_doctest.py
tests/test_pango.py
tests/test_pangocairo.py
tests/test_snippets.py
tests/test_stress.py
tests/test_svg.py
tests/text.utf8
