Metadata-Version: 1.0
Name: chimera
Version: 0.4.7
Summary:  Simple Image Generation 
Home-page: http://projects.objectrealms.net/projects/chimera
Author: Benjamin Saller
Author-email: bcsaller@objectrealms.net
License: GPL
Platform: Python >= 2.4
Classifier: Development Status :: 4 - Beta
Classifier: Intended Audience :: Developers
Classifier: Natural Language :: English
Classifier: Operating System :: OS Independent
Classifier: Programming Language :: Python
Classifier: Topic :: Multimedia :: Graphics :: Editors
Classifier: Topic :: Internet :: WWW/HTTP :: Dynamic Content
